saclm-1.0.0.dist-info/licenses/LICENSE
sclm/__init__.py
saclm-1.0.0.dist-info/METADATA
saclm-1.0.0.dist-info/WHEEL
saclm-1.0.0.dist-info/top_level.txt
saclm-1.0.0.dist-info/RECORD
