Metadata-Version: 2.4
Name: saclm
Version: 1.0.0
Summary: Stateful Coherent Language Models - Transformers with persistent memory
Home-page: https://github.com/Volgat/sclm
Author: Mike Amega
Author-email: contact@amewebstudio.com
Project-URL: Bug Tracker, https://github.com/Volgat/sclm/issues
Project-URL: Documentation, https://github.com/Volgat/sclm#readme
Project-URL: Paper, https://arxiv.org/abs/2512.XXXXX
Keywords: language model,transformer,stateful,coherence,memory,nlp,deep learning,pytorch
Classifier: Development Status :: 4 - Beta
Classifier: Intended Audience :: Developers
Classifier: Intended Audience :: Science/Research
Classifier: License :: Other/Proprietary License
Classifier: Operating System :: OS Independent
Classifier: Programming Language :: Python :: 3
Classifier: Programming Language :: Python :: 3.8
Classifier: Programming Language :: Python :: 3.9
Classifier: Programming Language :: Python :: 3.10
Classifier: Programming Language :: Python :: 3.11
Classifier: Topic :: Scientific/Engineering :: Artificial Intelligence
Classifier: Topic :: Text Processing :: Linguistic
Requires-Python: >=3.8
License-File: LICENSE
Requires-Dist: torch>=1.10.0
Requires-Dist: numpy>=1.19.0
Provides-Extra: dev
Requires-Dist: pytest>=6.0; extra == "dev"
Requires-Dist: pytest-cov>=2.0; extra == "dev"
Requires-Dist: black>=22.0; extra == "dev"
Requires-Dist: isort>=5.0; extra == "dev"
Requires-Dist: flake8>=4.0; extra == "dev"
Provides-Extra: transformers
Requires-Dist: transformers>=4.20.0; extra == "transformers"
Dynamic: author
Dynamic: author-email
Dynamic: classifier
Dynamic: description
Dynamic: description-content-type
Dynamic: home-page
Dynamic: keywords
Dynamic: license-file
Dynamic: project-url
Dynamic: provides-extra
Dynamic: requires-dist
Dynamic: requires-python
Dynamic: summary
